[{"data": [129, 105, 149, 115], "name": "Triangle"}, {"data": [121, 100, 131, 78], "name": "Fireball"}, {"data": [56, 50, 46, 47], "name": "Formation"}, {"data": [279, 240, 310, 289], "name": "Light"}, {"data": [153, 196, 182, 147], "name": "Circle"}, {"data": [13, 16, 17, 22], "name": "Chevron"}, {"data": [4, 8, 12, 7], "name": "Egg"}, {"data": [14, 16, 14, 20], "name": "Diamond"}, {"data": [18, 24, 15, 15], "name": "Cylinder"}, {"data": [58, 49, 54, 49], "name": "Disk"}, {"data": [31, 28, 37, 24], "name": "Changing"}]